clisechubman/__init__.py
clisechubman/__main__.py
clisechubman/aws_lambda_handler.py
clisechubman/clisechubman.py
clisechubman/main.py
clisechubman/py.typed
clisechubman-0.4.2.dist-info/WHEEL
clisechubman-0.4.2.dist-info/entry_points.txt
clisechubman-0.4.2.dist-info/METADATA
clisechubman-0.4.2.dist-info/RECORD
