Metadata-Version: 2.3
Name: clisechubman
Version: 0.4.2
Summary: Development flow as Paleofuturistic Python
Author: Paleofuturistic Python
Author-email: Paleofuturistic Python <me@here.now>
Classifier: License :: OSI Approved :: Apache Software License
Classifier: Programming Language :: Python :: 3.12
Requires-Dist: pyyaml==6.0.3
Requires-Dist: sechubman==0.2.0
Requires-Dist: typer==0.20.0
Requires-Dist: aws-lambda-powertools==3.23.0 ; extra == 'lambda'
Requires-Python: >=3.12
Provides-Extra: lambda
